setup.cfg
setup.py
basis_reduction/_init_.py
basis_reduction/basis_reduction.py
basis_reduction.egg-info/PKG-INFO
basis_reduction.egg-info/SOURCES.txt
basis_reduction.egg-info/dependency_links.txt
basis_reduction.egg-info/requires.txt
basis_reduction.egg-info/top_level.txt