Metadata-Version: 1.1
Name: basis-reduction
Version: 1.1.1
Summary: Python3 implementation of LLL and Gaussian method
Home-page: https://github.com/arturburiev/basis_reduction
Author: Artur Buriev
Author-email: arturburiev@yandex.com
License: MIT
Platform: UNKNOWN
Classifier: Development Status :: 3 - Alpha
Classifier: License :: OSI Approved :: MIT License
Classifier: Programming Language :: Python :: 3.6
Classifier: Programming Language :: Python :: 3.7
Classifier: Programming Language :: Python :: 3.8
Classifier: Programming Language :: Python :: 3 :: Only
